avcmt/__init__.py
avcmt/ai.py
avcmt/cli/__init__.py
avcmt/cli/commit.py
avcmt/cli/docs.py
avcmt/cli/main.py
avcmt/cli/release.py
avcmt/modules/commit_generator.py
avcmt/modules/doc_generator.py
avcmt/modules/release_manager.py
avcmt/prompt_templates/commit/commit_message.j2
avcmt/prompt_templates/docs/docstring.j2
avcmt/providers/__init__.py
avcmt/providers/openai.py
avcmt/providers/pollinations.py
avcmt/utils.py
avcmt_py-1.7.0.dist-info/LICENSE
avcmt_py-1.7.0.dist-info/METADATA
avcmt_py-1.7.0.dist-info/NOTICE
avcmt_py-1.7.0.dist-info/WHEEL
avcmt_py-1.7.0.dist-info/entry_points.txt
avcmt_py-1.7.0.dist-info/RECORD
