Metadata-Version: 2.3
Name: avcmt-py
Version: 1.7.0
Summary: avcmt-py: AI-Powered Semantic Release Style Git Commit Automation for Python Project.
License: Apache-2.0
Author: Andy Vandaric
Author-email: andyvandaric@gmail.com
Requires-Python: >=3.10,<4.0
Classifier: License :: OSI Approved :: Apache Software License
Classifier: Programming Language :: Python :: 3
Classifier: Programming Language :: Python :: 3.10
Classifier: Programming Language :: Python :: 3.11
Classifier: Programming Language :: Python :: 3.12
Classifier: Programming Language :: Python :: 3.13
Requires-Dist: jinja2 (>=3.1.4,<4.0.0)
Requires-Dist: requests (>=2.32,<3.0)
Requires-Dist: rich (>=14.0.0,<15.0.0)
Requires-Dist: toml (>=0.10.2,<0.11.0)
Requires-Dist: typer[all] (>=0.12.3,<0.13.0)
Project-URL: Documentation, https://avcmt.avandaric.live/docs
Project-URL: Homepage, https://avcmt.avandaric.live
Project-URL: Repository, https://github.com/andyvandaric/avcmt-py
